oc_toolbox/__init__.py
oc_toolbox/data.py
oc_toolbox/df.py
oc_toolbox/image.py
oc_toolbox/kaggle.py
oc_toolbox/ml.py
oc_toolbox/plot.py
oc_toolbox/stats.py
oc_toolbox/text.py
oc_toolbox/utils.py
oc_toolbox-0.5.0.dist-info/licenses/LICENSE
oc_toolbox-0.5.0.dist-info/METADATA
oc_toolbox-0.5.0.dist-info/WHEEL
oc_toolbox-0.5.0.dist-info/top_level.txt
oc_toolbox-0.5.0.dist-info/RECORD
